[
  {
    "category": "Research",
    "icon": "🔬",
    "items": [
      {
        "title": "Research Assistant — Social Network Research",
        "organization": "Stanford Cyber Policy Center",
        "period": "June 2023 – November 2024",
        "description": "Collected and coded social media data for a research project examining the use of search engines to propagate the consumption of low-quality information.",
        "link": "https://cyber.fsi.stanford.edu/"
      },
      {
        "title": "Student Researcher — AP Research: Investment Analysis",
        "organization": "El Toro High School",
        "period": "August 2024 – June 2025",
        "description": "Designed and executed an original study comparing the effectiveness of fundamental vs. technical investment analysis. Presented findings to an AP Research-certified panel and produced a full academic paper and literature review.",
        "link": null
      }
    ]
  },
  {
    "category": "Leadership & Service",
    "icon": "🤝",
    "items": [
      {
        "title": "Group Leader and Volunteer Tutor",
        "organization": "Global Cultural Education Foundation",
        "period": "September 2024 – August 2025",
        "description": "Led a delegation of 20 U.S. participants as senior student on a two-week immersion trip to Taiwan. Tutored Taiwanese middle schoolers via weekly Zoom sessions and coordinated lesson plans with local faculty. Developed Mandarin conversational fluency through immersion, earning the California Seal of Biliteracy.",
        "link": null
      },
      {
        "title": "Team Captain, Varsity Golf",
        "organization": "Athletic Leadership Council, El Toro High School",
        "period": "August 2024 – June 2025",
        "description": "Organized team strategy, served as liaison between coaching staff and team, and mentored underclassmen.",
        "link": null
      },
      {
        "title": "Member and Volunteer Tutor",
        "organization": "National Honors Society / Math Honors Society",
        "period": "August 2024 – June 2025",
        "description": "Tutored peers in math and core subjects at El Toro Public Library and El Toro Innovation Center. Provided academic support to ESL students, athletes, and demerit-recovery students.",
        "link": null
      }
    ]
  },
  {
    "category": "Skills & Interests",
    "icon": "💡",
    "items": [
      {
        "title": "Technical",
        "organization": "",
        "period": "",
        "description": "Python, Ubuntu, LaTeX, investment analysis.",
        "link": null
      },
      {
        "title": "Languages",
        "organization": "",
        "period": "",
        "description": "Mandarin Chinese (California Seal of Biliteracy), Indonesian (beginner).",
        "link": null
      },
      {
        "title": "Interests",
        "organization": "",
        "period": "",
        "description": "Piano (level 10 candidate), taekwondo (black belt), golf, investing.",
        "link": null
      }
    ]
  }
]
